SORNSim/__init__.py
SORNSim/create_readme.py
SORNSim/Exploration/UI_Base.py
SORNSim/Exploration/__init__.py
SORNSim/Exploration/Analysis/PCA.py
SORNSim/Exploration/Analysis/WP_testing.py
SORNSim/Exploration/Analysis/WiltingPriesemann.py
SORNSim/Exploration/Analysis/__init__.py
SORNSim/Exploration/Evolution/Computing_Devices.py
SORNSim/Exploration/Evolution/Evo_Plots.py
SORNSim/Exploration/Evolution/Evolution.py
SORNSim/Exploration/Evolution/Evolution_UI.py
SORNSim/Exploration/Evolution/Multithreaded_Evolution.py
SORNSim/Exploration/Evolution/NetworkEvaluationFunctions.py
SORNSim/Exploration/Evolution/__init__.py
SORNSim/Exploration/Evolution/exec.py
SORNSim/Exploration/Network_UI/Network_UI.py
SORNSim/Exploration/Network_UI/TabBase.py
SORNSim/Exploration/Network_UI/__init__.py
SORNSim/Exploration/Network_UI/Advanced_Tabs/__init__.py
SORNSim/Exploration/Network_UI/Advanced_Tabs/afferent_syn_attr_plot_tab.py
SORNSim/Exploration/Network_UI/Advanced_Tabs/buffer_tab.py
SORNSim/Exploration/Network_UI/Advanced_Tabs/criticality_tab.py
SORNSim/Exploration/Network_UI/Advanced_Tabs/scatter_tab.py
SORNSim/Exploration/Network_UI/Advanced_Tabs/stdp_buffer_tab.py
SORNSim/Exploration/Network_UI/Basic_Tabs/PCA_tab.py
SORNSim/Exploration/Network_UI/Basic_Tabs/__init__.py
SORNSim/Exploration/Network_UI/Basic_Tabs/fourier_tab.py
SORNSim/Exploration/Network_UI/Basic_Tabs/hist_tab.py
SORNSim/Exploration/Network_UI/Basic_Tabs/individual_weight_tab.py
SORNSim/Exploration/Network_UI/Basic_Tabs/info_tabs.py
SORNSim/Exploration/Network_UI/Basic_Tabs/multi_group_plot_tab.py
SORNSim/Exploration/Network_UI/Basic_Tabs/partition_tab.py
SORNSim/Exploration/Network_UI/Basic_Tabs/sidebar_activity_module.py
SORNSim/Exploration/Network_UI/Basic_Tabs/sidebar_fast_forward_module.py
SORNSim/Exploration/Network_UI/Basic_Tabs/sidebar_save_load_module.py
SORNSim/Exploration/Network_UI/Basic_Tabs/single_group_plot_tab.py
SORNSim/Exploration/Network_UI/Basic_Tabs/spiketrain_tab.py
SORNSim-0.2.0.dist-info/LICENSE
SORNSim-0.2.0.dist-info/METADATA
SORNSim-0.2.0.dist-info/WHEEL
SORNSim-0.2.0.dist-info/top_level.txt
SORNSim-0.2.0.dist-info/RECORD
